s2d2s/__init__.py
s2d2s-1.dist-info/LICENSE
s2d2s-1.dist-info/METADATA
s2d2s-1.dist-info/WHEEL
s2d2s-1.dist-info/top_level.txt
s2d2s-1.dist-info/RECORD
