Metadata-Version: 2.1
Name: s2d2s
Version: 1
Summary: Depth-to-Space and Space-to-Depth PyTorch implementation compatible with onnx
Author: lnstadrum
License: MIT License
Classifier: License :: OSI Approved :: MIT License
Classifier: Programming Language :: Python :: 3
License-File: LICENSE
